smc_trading/__init__.py
smc_trading/main_pipeline.py
smc_trading/smc_analysis.py
smc_trading/smc_screener.py
smc_screener-0.1.0.dist-info/METADATA
smc_screener-0.1.0.dist-info/WHEEL
smc_screener-0.1.0.dist-info/entry_points.txt
smc_screener-0.1.0.dist-info/licenses/LICENSE
smc_screener-0.1.0.dist-info/RECORD
