Metadata-Version: 2.4
Name: smc-screener
Version: 0.1.0
Summary: A Python package for Smart Money Concepts (SMC) analysis and stock screening
Author-email: Prasad <mr.xprasadx@gmail.com>
License-Expression: MIT
License-File: LICENSE
Keywords: finance,smc,stock-analysis,trading
Classifier: License :: OSI Approved :: MIT License
Classifier: Operating System :: OS Independent
Classifier: Programming Language :: Python :: 3
Requires-Python: >=3.6
Requires-Dist: gspread>=6.1.2
Requires-Dist: matplotlib>=3.9.2
Requires-Dist: numpy>=1.26.4
Requires-Dist: oauth2client>=4.1.3
Requires-Dist: pandas>=2.2.2
Requires-Dist: tqdm>=4.66.5
Requires-Dist: yfinance>=0.2.44
